datamaster_mcp/__init__.py
datamaster_mcp/main.py
datamaster_mcp/模块化重构方案.md
datamaster_mcp/重构示例-数据库模块.py
datamaster_mcp/重构示例-精简main.py
datamaster_mcp/config/__init__.py
datamaster_mcp/config/api_config.json
datamaster_mcp/config/api_config_manager.py
datamaster_mcp/config/api_connector.py
datamaster_mcp/config/api_data_storage.py
datamaster_mcp/config/config_manager.py
datamaster_mcp/config/data_transformer.py
datamaster_mcp/config/database_config.json
datamaster_mcp/config/database_manager.py
datamaster_mcp/core/__init__.py
datamaster_mcp/core/api_manager.py
datamaster_mcp/core/data_analysis.py
datamaster_mcp/core/data_processing.py
datamaster_mcp/core/database.py
datamaster_mcp/tools/__init__.py
datamaster_mcp/utils/__init__.py
datamaster_mcp_enhanced-1.0.0.dist-info/METADATA
datamaster_mcp_enhanced-1.0.0.dist-info/WHEEL
datamaster_mcp_enhanced-1.0.0.dist-info/entry_points.txt
datamaster_mcp_enhanced-1.0.0.dist-info/top_level.txt
datamaster_mcp_enhanced-1.0.0.dist-info/RECORD
